jmapper-0.2.0.data/scripts/mapper
jmapper-0.2.0.dist-info/top_level.txt
jmapper-0.2.0.dist-info/RECORD
jmapper-0.2.0.dist-info/METADATA
jmapper-0.2.0.dist-info/WHEEL
jmapper/libcoreir-lakelib.so
jmapper/cgra-mapper
jmapper/libcoreir-cgralib.so
jmapper/__init__.py
jmapper/.libs/libcoreir-841a9389.so
jmapper/.libs/libcoreirsim-3f9431cb.so
jmapper/.libs/libcoreir-commonlib-14afac6d.so
jmapper/.libs/libcoreir-lakelib-302c4aa8.so
jmapper/.libs/libverilogAST-3a41bea0.so
jmapper/.libs/libcoreir-cgralib-c44bbf14.so
jmapper/.libs/libcoreir-float-b1b1674f.so
