Metadata-Version: 2.1
Name: jmapper
Version: 0.2.0
Summary: Mapper for Jade CGRA
Home-page: https://github.com/Kuree/jmapper
Author: Keyi Zhang
Author-email: keyi@stanford.edu
License: UNKNOWN
Platform: UNKNOWN
